PrognosAIs/Constants.py
PrognosAIs/IO/ConfigLoader.py
PrognosAIs/IO/Configs.py
PrognosAIs/IO/DataGenerator.py
PrognosAIs/IO/LabelParser.py
PrognosAIs/IO/__init__.py
PrognosAIs/IO/utils.py
PrognosAIs/Model/Architectures/AlexNet.py
PrognosAIs/Model/Architectures/Architecture.py
PrognosAIs/Model/Architectures/DDSNet.py
PrognosAIs/Model/Architectures/DenseNet.py
PrognosAIs/Model/Architectures/InceptionNet.py
PrognosAIs/Model/Architectures/ResNet.py
PrognosAIs/Model/Architectures/UNet.py
PrognosAIs/Model/Architectures/VGG.py
PrognosAIs/Model/Architectures/__init__.py
PrognosAIs/Model/Callbacks.py
PrognosAIs/Model/Evaluators.py
PrognosAIs/Model/Losses.py
PrognosAIs/Model/Metrics.py
PrognosAIs/Model/Parsers.py
PrognosAIs/Model/Trainer.py
PrognosAIs/Model/__init__.py
PrognosAIs/Pipeline.py
PrognosAIs/Preprocessing/Preprocessors.py
PrognosAIs/Preprocessing/Samples.py
PrognosAIs/Preprocessing/__init__.py
PrognosAIs/__init__.py
prognosais-0.3.5.dist-info/LICENSE
prognosais-0.3.5.dist-info/WHEEL
prognosais-0.3.5.dist-info/METADATA
prognosais-0.3.5.dist-info/RECORD
