Metadata-Version: 2.1
Name: prognosais
Version: 0.3.5
Summary: Tool to quickly and easily train CNNs for medical imaging tasks
Home-page: https://github.com/Svdvoort/prognosais
License: Apache-2.0
Author: Sebastian van der Voort
Author-email: svoort25@gmail.com
Requires-Python: >=3.7,<3.9
Classifier: Development Status :: 3 - Alpha
Classifier: Intended Audience :: Developers
Classifier: License :: OSI Approved :: Apache Software License
Classifier: Operating System :: OS Independent
Classifier: Programming Language :: Python :: 3
Classifier: Programming Language :: Python :: 3.7
Classifier: Programming Language :: Python :: 3.8
Classifier: Topic :: Software Development :: Libraries :: Python Modules
Requires-Dist: PyYAML (>=5.3.1,<6.0.0)
Requires-Dist: SimpleITK (>=1.2.4,<3.0.0)
Requires-Dist: h5py (>=2.10.0,<3.0.0)
Requires-Dist: matplotlib (>=3.2.1,<4.0.0)
Requires-Dist: natsort (>=7.0.1,<8.0.0)
Requires-Dist: numba (>=0.49.1,<0.54.0)
Requires-Dist: numpy (>=1.18,<2.0)
Requires-Dist: pandas (>=1.0.3,<2.0.0)
Requires-Dist: psutil (>=5.7.0,<6.0.0)
Requires-Dist: scikit-learn (>=0.23,<0.25)
Requires-Dist: slurmpie (>=0.4.0,<0.5.0)
Requires-Dist: tensorboard_plugin_profile (>=2.2.0,<3.0.0)
Requires-Dist: tensorflow (>=2.2.0)
Requires-Dist: tensorflow-addons (>=0.11)
Requires-Dist: tensorflow-io (>=0.15)
Project-URL: Repository, https://github.com/Svdvoort/prognosais
